hatchhello/__about__.py
hatchhello/__about__.py~
hatchhello/__init__.py
hatchhello/hello.py
hatchhello-0.0.3.dist-info/METADATA
hatchhello-0.0.3.dist-info/WHEEL
hatchhello-0.0.3.dist-info/license_files/LICENSE.txt
hatchhello-0.0.3.dist-info/RECORD
