Metadata-Version: 2.1
Name: hatchhello
Version: 0.0.3
Summary: This program says hello.
Project-URL: Documentation, https://github.com/unknown/hatchhello#readme
Project-URL: Issues, https://github.com/unknown/hatchhello/issues
Project-URL: Source, https://github.com/unknown/hatchhello
Author-email: Jeremy Bryant <jb@jeremybryant.net>
Classifier: Development Status :: 4 - Beta
Classifier: Programming Language :: Python
Classifier: Programming Language :: Python :: 3.10
Classifier: Programming Language :: Python :: 3.7
Classifier: Programming Language :: Python :: 3.8
Classifier: Programming Language :: Python :: 3.9
Classifier: Programming Language :: Python :: Implementation :: CPython
Classifier: Programming Language :: Python :: Implementation :: PyPy
Requires-Python: >=3.7
